clients/__init__.py
clients/admin.py
clients/apps.py
clients/static/css/clients/bethany_ds.css
clients/static/css/clients/medilab_ds.css
clients/static/img/clients/amc.png
clients/static/img/clients/cmc.png
clients/static/img/clients/khmc.png
clients/static/img/clients/pnuh.png
clients/static/img/clients/sev.png
clients/static/img/clients/smc.png
clients/static/img/clients/snuh.png
clients/templates/clients/_common.html
clients/templates/clients/bethany_ds.html
clients/templates/clients/medilab_ds.html
clients/templatetags/__init__.py
clients/templatetags/clients_tags.py
django_clients_ds-0.0.1.dist-info/LICENSE
django_clients_ds-0.0.1.dist-info/METADATA
django_clients_ds-0.0.1.dist-info/WHEEL
django_clients_ds-0.0.1.dist-info/top_level.txt
django_clients_ds-0.0.1.dist-info/RECORD
