Metadata-Version: 2.1
Name: django-clients-ds
Version: 0.0.1
Summary: clients part for demiansoft
Home-page: https://www.demiansoft.com
Author: hyungjin kim
Author-email: hj3415@gmail.com
License: UNKNOWN
Project-URL: Bug Tracker, https://pypi.org/project/util-demian/
Platform: UNKNOWN
Classifier: License :: OSI Approved :: BSD License
Classifier: Operating System :: OS Independent
Classifier: Programming Language :: Python :: 3
Requires-Python: >=3.8
License-File: LICENSE
Requires-Dist: Django (>=3.2.9)
